{"nodes": [{"id": "c_users_krish_zenithos_os_quick_start_md", "label": "QUICK_START.md", "file_type": "document", "source_file": "QUICK_START.md", "source_location": "L1"}, {"id": "os_quick_start_zenithos_quick_start", "label": "ZenithOS Quick Start", "file_type": "document", "source_file": "QUICK_START.md", "source_location": "L1"}, {"id": "os_quick_start_build_the_seed_iso", "label": "Build The Seed ISO", "file_type": "document", "source_file": "QUICK_START.md", "source_location": "L3"}, {"id": "os_quick_start_blank_disk_install_vm", "label": "Blank-Disk Install VM", "file_type": "document", "source_file": "QUICK_START.md", "source_location": "L25"}, {"id": "os_quick_start_smoke_checks", "label": "Smoke Checks", "file_type": "document", "source_file": "QUICK_START.md", "source_location": "L70"}, {"id": "os_quick_start_development_persistence", "label": "Development Persistence", "file_type": "document", "source_file": "QUICK_START.md", "source_location": "L93"}], "edges": [{"source": "c_users_krish_zenithos_os_quick_start_md", "target": "os_quick_start_zenithos_quick_start", "relation": "contains", "confidence": "EXTRACTED", "source_file": "QUICK_START.md", "source_location": "L1", "weight": 1.0}, {"source": "os_quick_start_zenithos_quick_start", "target": "os_quick_start_build_the_seed_iso", "relation": "contains", "confidence": "EXTRACTED", "source_file": "QUICK_START.md", "source_location": "L3", "weight": 1.0}, {"source": "os_quick_start_zenithos_quick_start", "target": "os_quick_start_blank_disk_install_vm", "relation": "contains", "confidence": "EXTRACTED", "source_file": "QUICK_START.md", "source_location": "L25", "weight": 1.0}, {"source": "os_quick_start_zenithos_quick_start", "target": "os_quick_start_smoke_checks", "relation": "contains", "confidence": "EXTRACTED", "source_file": "QUICK_START.md", "source_location": "L70", "weight": 1.0}, {"source": "os_quick_start_zenithos_quick_start", "target": "os_quick_start_development_persistence", "relation": "contains", "confidence": "EXTRACTED", "source_file": "QUICK_START.md", "source_location": "L93", "weight": 1.0}], "input_tokens": 0, "output_tokens": 0}